tiny_thumbnail_engine/__init__.py
tiny_thumbnail_engine/app.py
tiny_thumbnail_engine/environ.py
tiny_thumbnail_engine/exceptions.py
tiny_thumbnail_engine/model.py
tiny_thumbnail_engine/py.typed
tiny_thumbnail_engine/server/__init__.py
tiny_thumbnail_engine/server/aws.py
tiny_thumbnail_engine/signing.py
tiny_thumbnail_engine/storage/__init__.py
tiny_thumbnail_engine/storage/protocol.py
tiny_thumbnail_engine/storage/s3.py
tiny_thumbnail_engine-0.3.1.dist-info/METADATA
tiny_thumbnail_engine-0.3.1.dist-info/LICENSE
tiny_thumbnail_engine-0.3.1.dist-info/WHEEL
tiny_thumbnail_engine-0.3.1.dist-info/RECORD
