Metadata-Version: 2.1
Name: tiny-thumbnail-engine
Version: 0.3.1
Summary: Tiny Thumbnail Engine
Home-page: https://github.com/john-parton/tiny-thumbnail-engine
License: MIT
Author: John Parton
Author-email: john.parton.iv@gmail.com
Requires-Python: >=3.7,<4.0
Classifier: Development Status :: 1 - Planning
Classifier: License :: OSI Approved :: MIT License
Classifier: Programming Language :: Python :: 3
Classifier: Programming Language :: Python :: 3.7
Classifier: Programming Language :: Python :: 3.8
Classifier: Programming Language :: Python :: 3.9
Classifier: Programming Language :: Python :: 3.10
Classifier: Programming Language :: Python :: 3.11
Provides-Extra: server
Requires-Dist: attrs (>=22.1.0,<23.0.0)
Requires-Dist: boto3 (>=1.26.32,<2.0.0) ; extra == "server"
Requires-Dist: pyvips (>=2.2.1,<3.0.0) ; extra == "server"
Project-URL: Changelog, https://github.com/john-parton/tiny-thumbnail-engine/releases
Project-URL: Documentation, https://tiny-thumbnail-engine.readthedocs.io
Project-URL: Repository, https://github.com/john-parton/tiny-thumbnail-engine
